watchopen/__init__.py
watchopen/__main__.py
watch_open-0.0.1.dist-info/LICENSE
watch_open-0.0.1.dist-info/METADATA
watch_open-0.0.1.dist-info/WHEEL
watch_open-0.0.1.dist-info/entry_points.txt
watch_open-0.0.1.dist-info/top_level.txt
watch_open-0.0.1.dist-info/RECORD
