Metadata-Version: 2.1
Name: watch-open
Version: 0.0.1
Summary: Opens a copy of file on every change
Home-page: https://github.com/mugiseyebrows/watch-open
Author: Stanislav Doronin
Author-email: mugisbrows@gmail.com
License: UNKNOWN
Platform: UNKNOWN
Requires-Dist: eventloop
Requires-Dist: colorama
